nti.webhooks-0.0.6-py3.9-nspkg.pth
nti/webhooks/__init__.py
nti/webhooks/_schema.py
nti/webhooks/_util.py
nti/webhooks/api.py
nti/webhooks/attempts.py
nti/webhooks/configure.zcml
nti/webhooks/datamanager.py
nti/webhooks/delivery_manager.py
nti/webhooks/destination_validator.py
nti/webhooks/dialect.py
nti/webhooks/externalization.py
nti/webhooks/generations.py
nti/webhooks/interfaces.py
nti/webhooks/meta.zcml
nti/webhooks/permissions.zcml
nti/webhooks/subscribers.py
nti/webhooks/subscribers.zcml
nti/webhooks/subscribers_promiscuous.zcml
nti/webhooks/subscriptions.py
nti/webhooks/testing.py
nti/webhooks/zcml.py
nti/webhooks/tests/__init__.py
nti/webhooks/tests/test_attempts.py
nti/webhooks/tests/test_docs.py
nti/webhooks/tests/test_generations.py
nti/webhooks/tests/test_subscriptions.py
nti/webhooks/tests/test_zcml.py
nti.webhooks-0.0.6.dist-info/LICENSE
nti.webhooks-0.0.6.dist-info/METADATA
nti.webhooks-0.0.6.dist-info/WHEEL
nti.webhooks-0.0.6.dist-info/namespace_packages.txt
nti.webhooks-0.0.6.dist-info/top_level.txt
nti.webhooks-0.0.6.dist-info/RECORD
