Metadata-Version: 2.1
Name: nti.webhooks
Version: 0.0.6
Summary: Python/Zope3 server-side webhooks implementation using ZODB and requests.
Home-page: https://github.com/NextThought/nti.webhooks
Author: Jason Madden
Author-email: jason@nextthought.com
License: Apache
Project-URL: Documentation, https://ntiwebhooks.readthedocs.io/en/latest/
Keywords: webhook server event zope ZODB
Platform: UNKNOWN
Classifier: Intended Audience :: Developers
Classifier: Natural Language :: English
Classifier: Operating System :: OS Independent
Classifier: Programming Language :: Python :: 2
Classifier: Programming Language :: Python :: 2.7
Classifier: Programming Language :: Python :: 3
Classifier: Programming Language :: Python :: 3.6
Classifier: Programming Language :: Python :: 3.7
Classifier: Programming Language :: Python :: 3.8
Classifier: Programming Language :: Python :: 3.9
Classifier: Programming Language :: Python :: Implementation :: CPython
Classifier: Programming Language :: Python :: Implementation :: PyPy
Classifier: Framework :: Zope3
Classifier: Development Status :: 1 - Planning
License-File: LICENSE
Requires-Dist: zope.authentication
Requires-Dist: zope.annotation
Requires-Dist: zope.interface (>=5.4.0)
Requires-Dist: zope.container
Requires-Dist: zope.security
Requires-Dist: zope.principalregistry
Requires-Dist: zope.componentvocabulary
Requires-Dist: zope.vocabularyregistry
Requires-Dist: zope.securitypolicy
Requires-Dist: zope.generations
Requires-Dist: zope.site
Requires-Dist: nti.site (>=2.2.0)
Requires-Dist: nti.zodb (>=1.3.0)
Requires-Dist: nti.externalization (>=2.3.0)
Requires-Dist: nti.schema (>=1.16.0)
Requires-Dist: setuptools
Requires-Dist: transaction (>=3.0.1)
Requires-Dist: futures ; python_version == "2.7"
Provides-Extra: docs
Requires-Dist: Sphinx ; extra == 'docs'
Requires-Dist: sphinx-rtd-theme (==0.5.2) ; extra == 'docs'
Requires-Dist: docutils (<0.17) ; extra == 'docs'
Requires-Dist: repoze.sphinx.autointerface ; extra == 'docs'
Requires-Dist: coverage ; extra == 'docs'
Requires-Dist: nti.testing (>=3.0.0) ; extra == 'docs'
Requires-Dist: fudge ; extra == 'docs'
Requires-Dist: zope.testrunner ; extra == 'docs'
Requires-Dist: zope.lifecycleevent ; extra == 'docs'
Requires-Dist: zope.securitypolicy ; extra == 'docs'
Requires-Dist: responses ; extra == 'docs'
Requires-Dist: zope.pluggableauth ; extra == 'docs'
Requires-Dist: zope.app.appsetup ; extra == 'docs'
Provides-Extra: test
Requires-Dist: coverage ; extra == 'test'
Requires-Dist: nti.testing (>=3.0.0) ; extra == 'test'
Requires-Dist: fudge ; extra == 'test'
Requires-Dist: zope.testrunner ; extra == 'test'
Requires-Dist: zope.lifecycleevent ; extra == 'test'
Requires-Dist: zope.securitypolicy ; extra == 'test'
Requires-Dist: responses ; extra == 'test'
Requires-Dist: zope.pluggableauth ; extra == 'test'
Requires-Dist: zope.app.appsetup ; extra == 'test'
